{"nodes": [{"id": "c_users_augus_loyalty_cards_src_app_dashboard_cards_id_viptierssection_tsx", "label": "VipTiersSection.tsx", "file_type": "code", "source_file": "C:\\Users\\augus\\loyalty-cards\\src\\app\\dashboard\\cards\\[id]\\VipTiersSection.tsx", "source_location": "L1"}, {"id": "viptierssection_resetform", "label": "resetForm()", "file_type": "code", "source_file": "C:\\Users\\augus\\loyalty-cards\\src\\app\\dashboard\\cards\\[id]\\VipTiersSection.tsx", "source_location": "L49"}, {"id": "viptierssection_startedit", "label": "startEdit()", "file_type": "code", "source_file": "C:\\Users\\augus\\loyalty-cards\\src\\app\\dashboard\\cards\\[id]\\VipTiersSection.tsx", "source_location": "L51"}, {"id": "viptierssection_handlesave", "label": "handleSave()", "file_type": "code", "source_file": "C:\\Users\\augus\\loyalty-cards\\src\\app\\dashboard\\cards\\[id]\\VipTiersSection.tsx", "source_location": "L61"}, {"id": "viptierssection_handledelete", "label": "handleDelete()", "file_type": "code", "source_file": "C:\\Users\\augus\\loyalty-cards\\src\\app\\dashboard\\cards\\[id]\\VipTiersSection.tsx", "source_location": "L92"}, {"id": "viptierssection_handlemoveup", "label": "handleMoveUp()", "file_type": "code", "source_file": "C:\\Users\\augus\\loyalty-cards\\src\\app\\dashboard\\cards\\[id]\\VipTiersSection.tsx", "source_location": "L98"}, {"id": "viptierssection_handlemovedown", "label": "handleMoveDown()", "file_type": "code", "source_file": "C:\\Users\\augus\\loyalty-cards\\src\\app\\dashboard\\cards\\[id]\\VipTiersSection.tsx", "source_location": "L108"}, {"id": "viptierssection_handleloaddefaults", "label": "handleLoadDefaults()", "file_type": "code", "source_file": "C:\\Users\\augus\\loyalty-cards\\src\\app\\dashboard\\cards\\[id]\\VipTiersSection.tsx", "source_location": "L118"}, {"id": "viptierssection_tiercolor", "label": "tierColor()", "file_type": "code", "source_file": "C:\\Users\\augus\\loyalty-cards\\src\\app\\dashboard\\cards\\[id]\\VipTiersSection.tsx", "source_location": "L136"}], "edges": [{"source": "c_users_augus_loyalty_cards_src_app_dashboard_cards_id_viptierssection_tsx", "target": "react", "relation": "imports_from", "confidence": "EXTRACTED", "source_file": "C:\\Users\\augus\\loyalty-cards\\src\\app\\dashboard\\cards\\[id]\\VipTiersSection.tsx", "source_location": "L3", "weight": 1.0}, {"source": "c_users_augus_loyalty_cards_src_app_dashboard_cards_id_viptierssection_tsx", "target": "viptierssection_resetform", "relation": "contains", "confidence": "EXTRACTED", "source_file": "C:\\Users\\augus\\loyalty-cards\\src\\app\\dashboard\\cards\\[id]\\VipTiersSection.tsx", "source_location": "L49", "weight": 1.0}, {"source": "c_users_augus_loyalty_cards_src_app_dashboard_cards_id_viptierssection_tsx", "target": "viptierssection_startedit", "relation": "contains", "confidence": "EXTRACTED", "source_file": "C:\\Users\\augus\\loyalty-cards\\src\\app\\dashboard\\cards\\[id]\\VipTiersSection.tsx", "source_location": "L51", "weight": 1.0}, {"source": "c_users_augus_loyalty_cards_src_app_dashboard_cards_id_viptierssection_tsx", "target": "viptierssection_handlesave", "relation": "contains", "confidence": "EXTRACTED", "source_file": "C:\\Users\\augus\\loyalty-cards\\src\\app\\dashboard\\cards\\[id]\\VipTiersSection.tsx", "source_location": "L61", "weight": 1.0}, {"source": "c_users_augus_loyalty_cards_src_app_dashboard_cards_id_viptierssection_tsx", "target": "viptierssection_handledelete", "relation": "contains", "confidence": "EXTRACTED", "source_file": "C:\\Users\\augus\\loyalty-cards\\src\\app\\dashboard\\cards\\[id]\\VipTiersSection.tsx", "source_location": "L92", "weight": 1.0}, {"source": "c_users_augus_loyalty_cards_src_app_dashboard_cards_id_viptierssection_tsx", "target": "viptierssection_handlemoveup", "relation": "contains", "confidence": "EXTRACTED", "source_file": "C:\\Users\\augus\\loyalty-cards\\src\\app\\dashboard\\cards\\[id]\\VipTiersSection.tsx", "source_location": "L98", "weight": 1.0}, {"source": "c_users_augus_loyalty_cards_src_app_dashboard_cards_id_viptierssection_tsx", "target": "viptierssection_handlemovedown", "relation": "contains", "confidence": "EXTRACTED", "source_file": "C:\\Users\\augus\\loyalty-cards\\src\\app\\dashboard\\cards\\[id]\\VipTiersSection.tsx", "source_location": "L108", "weight": 1.0}, {"source": "c_users_augus_loyalty_cards_src_app_dashboard_cards_id_viptierssection_tsx", "target": "viptierssection_handleloaddefaults", "relation": "contains", "confidence": "EXTRACTED", "source_file": "C:\\Users\\augus\\loyalty-cards\\src\\app\\dashboard\\cards\\[id]\\VipTiersSection.tsx", "source_location": "L118", "weight": 1.0}, {"source": "c_users_augus_loyalty_cards_src_app_dashboard_cards_id_viptierssection_tsx", "target": "viptierssection_tiercolor", "relation": "contains", "confidence": "EXTRACTED", "source_file": "C:\\Users\\augus\\loyalty-cards\\src\\app\\dashboard\\cards\\[id]\\VipTiersSection.tsx", "source_location": "L136", "weight": 1.0}, {"source": "viptierssection_handlesave", "target": "viptierssection_resetform", "relation": "calls", "confidence": "EXTRACTED", "source_file": "C:\\Users\\augus\\loyalty-cards\\src\\app\\dashboard\\cards\\[id]\\VipTiersSection.tsx", "source_location": "L85", "weight": 1.0}]}