{"nodes": [{"id": "c_users_augus_loyalty_cards_src_components_adminupgraderequests_tsx", "label": "AdminUpgradeRequests.tsx", "file_type": "code", "source_file": "C:\\Users\\augus\\loyalty-cards\\src\\components\\AdminUpgradeRequests.tsx", "source_location": "L1"}, {"id": "adminupgraderequests_itemlabel", "label": "itemLabel()", "file_type": "code", "source_file": "C:\\Users\\augus\\loyalty-cards\\src\\components\\AdminUpgradeRequests.tsx", "source_location": "L31"}, {"id": "adminupgraderequests_approve", "label": "approve()", "file_type": "code", "source_file": "C:\\Users\\augus\\loyalty-cards\\src\\components\\AdminUpgradeRequests.tsx", "source_location": "L42"}], "edges": [{"source": "c_users_augus_loyalty_cards_src_components_adminupgraderequests_tsx", "target": "react", "relation": "imports_from", "confidence": "EXTRACTED", "source_file": "C:\\Users\\augus\\loyalty-cards\\src\\components\\AdminUpgradeRequests.tsx", "source_location": "L3", "weight": 1.0}, {"source": "c_users_augus_loyalty_cards_src_components_adminupgraderequests_tsx", "target": "adminupgraderequests_itemlabel", "relation": "contains", "confidence": "EXTRACTED", "source_file": "C:\\Users\\augus\\loyalty-cards\\src\\components\\AdminUpgradeRequests.tsx", "source_location": "L31", "weight": 1.0}, {"source": "c_users_augus_loyalty_cards_src_components_adminupgraderequests_tsx", "target": "adminupgraderequests_approve", "relation": "contains", "confidence": "EXTRACTED", "source_file": "C:\\Users\\augus\\loyalty-cards\\src\\components\\AdminUpgradeRequests.tsx", "source_location": "L42", "weight": 1.0}]}